CMakeLists.txt
MANIFEST.in
README.en-us.md
README.md
pyproject.toml
setup.py
librmcs/example/CMakeLists.txt
librmcs/librmcs/device/dji_motor.hpp
librmcs/librmcs/device/dr16.hpp
librmcs/librmcs/device/imu.hpp
librmcs/librmcs/forwarder/cboard.hpp
librmcs/librmcs/utility/endian_promise.hpp
librmcs/librmcs/utility/logging.hpp
librmcs/librmcs/utility/pid_calculator.hpp
librmcs/librmcs/utility/ring_buffer.hpp
librmcspy/__init__.py
librmcspy.egg-info/PKG-INFO
librmcspy.egg-info/SOURCES.txt
librmcspy.egg-info/dependency_links.txt
librmcspy.egg-info/not-zip-safe
librmcspy.egg-info/requires.txt
librmcspy.egg-info/top_level.txt
pybind11/CMakeLists.txt
pybind11/LICENSE
pybind11/include/pybind11/attr.h
pybind11/include/pybind11/buffer_info.h
pybind11/include/pybind11/cast.h
pybind11/include/pybind11/chrono.h
pybind11/include/pybind11/common.h
pybind11/include/pybind11/complex.h
pybind11/include/pybind11/eigen.h
pybind11/include/pybind11/embed.h
pybind11/include/pybind11/eval.h
pybind11/include/pybind11/functional.h
pybind11/include/pybind11/gil.h
pybind11/include/pybind11/gil_safe_call_once.h
pybind11/include/pybind11/iostream.h
pybind11/include/pybind11/numpy.h
pybind11/include/pybind11/operators.h
pybind11/include/pybind11/options.h
pybind11/include/pybind11/pybind11.h
pybind11/include/pybind11/pytypes.h
pybind11/include/pybind11/stl.h
pybind11/include/pybind11/stl_bind.h
pybind11/include/pybind11/type_caster_pyobject_ptr.h
pybind11/include/pybind11/typing.h
pybind11/include/pybind11/detail/class.h
pybind11/include/pybind11/detail/common.h
pybind11/include/pybind11/detail/cpp_conduit.h
pybind11/include/pybind11/detail/descr.h
pybind11/include/pybind11/detail/exception_translation.h
pybind11/include/pybind11/detail/init.h
pybind11/include/pybind11/detail/internals.h
pybind11/include/pybind11/detail/type_caster_base.h
pybind11/include/pybind11/detail/typeid.h
pybind11/include/pybind11/detail/value_and_holder.h
pybind11/include/pybind11/eigen/common.h
pybind11/include/pybind11/eigen/matrix.h
pybind11/include/pybind11/eigen/tensor.h
pybind11/include/pybind11/stl/filesystem.h
pybind11/tests/CMakeLists.txt
pybind11/tests/test_cmake_build/CMakeLists.txt
