Metadata-Version: 2.1
Name: librmcspy
Version: 0.0.2
Summary: A portable python library which implements the core functionality of RMCS.
Author: Zihan Qin
Author-email: zihanqin2048@gmail.com
Requires-Python: >=3.7
Provides-Extra: test
Requires-Dist: pytest>=6.0; extra == "test"
